job_notifications/__init__.py
job_notifications/mail_services.py
job_notifications/notifications.py
job_notifications/py.typed
job_notifications/utils/__init__.py
job_notifications/utils/exceptions.py
job_notifications/utils/handle_exception.py
job_notifications/utils/helpers.py
job_notifications-2.0.0.dist-info/LICENSE
job_notifications-2.0.0.dist-info/METADATA
job_notifications-2.0.0.dist-info/WHEEL
job_notifications-2.0.0.dist-info/top_level.txt
job_notifications-2.0.0.dist-info/RECORD
